RocketChatBot.py
RocketChatAPIBot-0.1.4.dist-info/LICENSE.txt
RocketChatAPIBot-0.1.4.dist-info/METADATA
RocketChatAPIBot-0.1.4.dist-info/WHEEL
RocketChatAPIBot-0.1.4.dist-info/top_level.txt
RocketChatAPIBot-0.1.4.dist-info/RECORD
