Metadata-Version: 2.1
Name: RocketChatAPIBot
Version: 0.1.4
Summary: REST API based bot for Rocket.Chat
Home-page: https://github.com/jadolg/RocketChatBot
Author: Jorge Alberto Díaz Orozco
Author-email: diazorozcoj@gmail.com
License: MIT
Platform: UNKNOWN
Requires-Dist: rocketchat-API
